PerfProgTesting/__init__.py
PerfProgTesting/settings.py
PerfProgTesting/urls.py
PerfProgTesting/wsgi.py
ecom/__init__.py
ecom/settings.py
ecom/urls.py
ecom/wsgi.py
website/__init__.py
website/admin.py
website/apps.py
website/models.py
website/tests.py
website/views.py
website/migrations/0001_initial.py
website/migrations/__init__.py
PerfProgTesting-0.4.dist-info/LICENSE
PerfProgTesting-0.4.dist-info/METADATA
PerfProgTesting-0.4.dist-info/WHEEL
PerfProgTesting-0.4.dist-info/entry_points.txt
PerfProgTesting-0.4.dist-info/top_level.txt
PerfProgTesting-0.4.dist-info/RECORD
